<SOLICITUD_AUTORIZACION>
 <DTE>
	<TIEMPO> Guatemala, 15/01/2021 15:25 hrs. </TIEMPO>
	<REFERENCIA>A1990</REFERENCIA>
	<NIT_EMISOR>24959111</NIT_EMISOR>
	<NIT_RECEPTOR>26706288</NIT_RECEPTOR>
	<VALOR>100.00</VALOR>
	<IVA>12.00</IVA>
	<TOTAL>112.00</TOTAL>
 </DTE>
 <DTE>
	<TIEMPO> Guatemala, 15/01/2021 19:25 hrs. </TIEMPO>
	<REFERENCIA> B1990 </REFERENCIA>
	<NIT_EMISOR>20584458</NIT_EMISOR>
	<NIT_RECEPTOR>16445929</NIT_RECEPTOR>
	<VALOR>200.00</VALOR>
	<IVA>24.00</IVA>
	<TOTAL>224.00</TOTAL>
 </DTE>
 <DTE>
	<TIEMPO> Guatemala, 16/01/2021 11:25 hrs. </TIEMPO>
	<REFERENCIA>C1990</REFERENCIA>
	<NIT_EMISOR> 4884 </NIT_EMISOR>
	<NIT_RECEPTOR> 9393939393 </NIT_RECEPTOR>
	<VALOR> 300.00 </VALOR>
	<IVA> 36.00 </IVA>
	<TOTAL> 136.00 </TOTAL>
 </DTE>
</SOLICITUD_AUTORIZACION>